odoo/addons/project_task_personal_stage_auto_fold/README.rst
odoo/addons/project_task_personal_stage_auto_fold/__init__.py
odoo/addons/project_task_personal_stage_auto_fold/__manifest__.py
odoo/addons/project_task_personal_stage_auto_fold/i18n/es.po
odoo/addons/project_task_personal_stage_auto_fold/i18n/hr.po
odoo/addons/project_task_personal_stage_auto_fold/i18n/it.po
odoo/addons/project_task_personal_stage_auto_fold/i18n/project_task_personal_stage_auto_fold.pot
odoo/addons/project_task_personal_stage_auto_fold/i18n/pt_BR.po
odoo/addons/project_task_personal_stage_auto_fold/models/__init__.py
odoo/addons/project_task_personal_stage_auto_fold/models/project_task.py
odoo/addons/project_task_personal_stage_auto_fold/readme/CONFIGURE.md
odoo/addons/project_task_personal_stage_auto_fold/readme/CONTRIBUTORS.md
odoo/addons/project_task_personal_stage_auto_fold/readme/DESCRIPTION.md
odoo/addons/project_task_personal_stage_auto_fold/readme/USAGE.md
odoo/addons/project_task_personal_stage_auto_fold/static/description/icon.png
odoo/addons/project_task_personal_stage_auto_fold/static/description/index.html
odoo/addons/project_task_personal_stage_auto_fold/tests/__init__.py
odoo/addons/project_task_personal_stage_auto_fold/tests/test_personal_stages.py
odoo_addon_project_task_personal_stage_auto_fold-18.0.1.0.1.dist-info/METADATA
odoo_addon_project_task_personal_stage_auto_fold-18.0.1.0.1.dist-info/WHEEL
odoo_addon_project_task_personal_stage_auto_fold-18.0.1.0.1.dist-info/top_level.txt
odoo_addon_project_task_personal_stage_auto_fold-18.0.1.0.1.dist-info/RECORD
